barmpy/__init__.py
barmpy/barn.py
barmpy-1.2.3.dist-info/licenses/LICENSE
examples/__init__.py
examples/ols.py
test/__init__.py
test/test_barn.py
test/test_nn.py
test/test_tfnn.py
barmpy-1.2.3.dist-info/METADATA
barmpy-1.2.3.dist-info/WHEEL
barmpy-1.2.3.dist-info/top_level.txt
barmpy-1.2.3.dist-info/RECORD
