Metadata-Version: 2.4
Name: barmpy
Version: 1.2.3
Summary: Bayesian Additive Regression Models
Home-page: https://github.com/dvbuntu/barmpy
Author: Danielle Van Boxel
Author-email: Danielle Van Boxel <vanboxel@arizona.edu>
Project-URL: Homepage, https://github.com/dvbuntu/barmpy
Project-URL: Issues, https://github.com/dvbuntu/barmpy/issues
Project-URL: Documentation, https://dvbuntu.github.io/barmpy/
Classifier: Programming Language :: Python :: 3
Classifier: License :: OSI Approved :: MIT License
Classifier: Operating System :: OS Independent
Classifier: Topic :: Scientific/Engineering :: Mathematics
Requires-Python: >=3.8
License-File: LICENSE
Dynamic: author
Dynamic: home-page
Dynamic: license-file
